<?xml version="1.0" encoding="UTF-8" ?>
<!DOCTYPE mapper PUBLIC "-//mybatis.org//DTD Mapper 3.0//EN" "http://mybatis.org/dtd/mybatis-3-mapper.dtd" >
<mapper namespace="com.redfinger.manager.common.mapper.AssessOptionMapper" >
  <resultMap id="BaseResultMap" type="com.redfinger.manager.common.domain.AssessOption" >
    <!--
      WARNING - @mbggenerated
      This element is automatically generated by MyBatis Generator, do not modify.
      This element was generated on Wed Mar 23 14:42:45 CST 2016.
    -->
    <id column="id" property="id" jdbcType="INTEGER" />
    <result column="name" property="name" jdbcType="VARCHAR" />
    <result column="status" property="status" jdbcType="VARCHAR" />
    <result column="creater" property="creater" jdbcType="VARCHAR" />
    <result column="create_time" property="createTime" jdbcType="TIMESTAMP" />
    <result column="modifier" property="modifier" jdbcType="VARCHAR" />
    <result column="modify_time" property="modifyTime" jdbcType="TIMESTAMP" />
    <result column="enable_status" property="enableStatus" jdbcType="VARCHAR" />
    <result column="remark" property="remark" jdbcType="VARCHAR" />
    <result column="point" property="point" jdbcType="INTEGER" />
    <result column="reorder" property="reorder" jdbcType="INTEGER" />
    <result column="keyword" property="keyword" jdbcType="VARCHAR" />
  </resultMap>
  <sql id="Example_Where_Clause" >
    <!--
      WARNING - @mbggenerated
      This element is automatically generated by MyBatis Generator, do not modify.
      This element was generated on Wed Mar 23 14:42:45 CST 2016.
    -->
    <where >
      <foreach collection="oredCriteria" item="criteria" separator="or" >
        <if test="criteria.valid" >
          <trim prefix="(" suffix=")" prefixOverrides="and" >
            <foreach collection="criteria.criteria" item="criterion" >
              <choose >
                <when test="criterion.noValue" >
                  and ${criterion.condition}
                </when>
                <when test="criterion.singleValue" >
                  and ${criterion.condition} #{criterion.value}
                </when>
                <when test="criterion.betweenValue" >
                  and ${criterion.condition} #{criterion.value} and #{criterion.secondValue}
                </when>
                <when test="criterion.listValue" >
                  and ${criterion.condition}
                  <foreach collection="criterion.value" item="listItem" open="(" close=")" separator="," >
                    #{listItem}
                  </foreach>
                </when>
              </choose>
            </foreach>
          </trim>
        </if>
      </foreach>
    </where>
  </sql>
  <sql id="Update_By_Example_Where_Clause" >
    <!--
      WARNING - @mbggenerated
      This element is automatically generated by MyBatis Generator, do not modify.
      This element was generated on Wed Mar 23 14:42:45 CST 2016.
    -->
    <where >
      <foreach collection="example.oredCriteria" item="criteria" separator="or" >
        <if test="criteria.valid" >
          <trim prefix="(" suffix=")" prefixOverrides="and" >
            <foreach collection="criteria.criteria" item="criterion" >
              <choose >
                <when test="criterion.noValue" >
                  and ${criterion.condition}
                </when>
                <when test="criterion.singleValue" >
                  and ${criterion.condition} #{criterion.value}
                </when>
                <when test="criterion.betweenValue" >
                  and ${criterion.condition} #{criterion.value} and #{criterion.secondValue}
                </when>
                <when test="criterion.listValue" >
                  and ${criterion.condition}
                  <foreach collection="criterion.value" item="listItem" open="(" close=")" separator="," >
                    #{listItem}
                  </foreach>
                </when>
              </choose>
            </foreach>
          </trim>
        </if>
      </foreach>
    </where>
  </sql>
  <sql id="Base_Column_List" >
    <!--
      WARNING - @mbggenerated
      This element is automatically generated by MyBatis Generator, do not modify.
      This element was generated on Wed Mar 23 14:42:45 CST 2016.
    -->
    id, name, status, creater, create_time, modifier, modify_time, enable_status, remark, 
    point, reorder, keyword
  </sql>
  <select id="selectByExample" resultMap="BaseResultMap" parameterType="com.redfinger.manager.common.domain.AssessOptionExample" >
    <!--
      WARNING - @mbggenerated
      This element is automatically generated by MyBatis Generator, do not modify.
      This element was generated on Wed Mar 23 14:42:45 CST 2016.
    -->
    select
    <if test="distinct" >
      distinct
    </if>
    <include refid="Base_Column_List" />
    from assess_option
    <if test="_parameter != null" >
      <include refid="Example_Where_Clause" />
    </if>
    <if test="orderByClause != null" >
      order by ${orderByClause}
    </if>
  </select>
  <select id="selectByPrimaryKey" resultMap="BaseResultMap" parameterType="java.lang.Integer" >
    <!--
      WARNING - @mbggenerated
      This element is automatically generated by MyBatis Generator, do not modify.
      This element was generated on Wed Mar 23 14:42:45 CST 2016.
    -->
    select 
    <include refid="Base_Column_List" />
    from assess_option
    where id = #{id,jdbcType=INTEGER}
  </select>
  <delete id="deleteByPrimaryKey" parameterType="java.lang.Integer" >
    <!--
      WARNING - @mbggenerated
      This element is automatically generated by MyBatis Generator, do not modify.
      This element was generated on Wed Mar 23 14:42:45 CST 2016.
    -->
    delete from assess_option
    where id = #{id,jdbcType=INTEGER}
  </delete>
  <delete id="deleteByExample" parameterType="com.redfinger.manager.common.domain.AssessOptionExample" >
    <!--
      WARNING - @mbggenerated
      This element is automatically generated by MyBatis Generator, do not modify.
      This element was generated on Wed Mar 23 14:42:45 CST 2016.
    -->
    delete from assess_option
    <if test="_parameter != null" >
      <include refid="Example_Where_Clause" />
    </if>
  </delete>
  <insert id="insert" parameterType="com.redfinger.manager.common.domain.AssessOption" >
    <!--
      WARNING - @mbggenerated
      This element is automatically generated by MyBatis Generator, do not modify.
      This element was generated on Wed Mar 23 14:42:45 CST 2016.
    -->
    <selectKey resultType="java.lang.Integer" keyProperty="id" order="BEFORE" >
      select nextval('seq_assess_option')
    </selectKey>
    insert into assess_option (id, name, status, 
      creater, create_time, modifier, 
      modify_time, enable_status, remark, 
      point, reorder, keyword
      )
    values (#{id,jdbcType=INTEGER}, #{name,jdbcType=VARCHAR}, #{status,jdbcType=VARCHAR}, 
      #{creater,jdbcType=VARCHAR}, #{createTime,jdbcType=TIMESTAMP}, #{modifier,jdbcType=VARCHAR}, 
      #{modifyTime,jdbcType=TIMESTAMP}, #{enableStatus,jdbcType=VARCHAR}, #{remark,jdbcType=VARCHAR}, 
      #{point,jdbcType=INTEGER}, #{reorder,jdbcType=INTEGER}, #{keyword,jdbcType=VARCHAR}
      )
  </insert>
  <insert id="insertSelective" parameterType="com.redfinger.manager.common.domain.AssessOption" >
    <!--
      WARNING - @mbggenerated
      This element is automatically generated by MyBatis Generator, do not modify.
      This element was generated on Wed Mar 23 14:42:45 CST 2016.
    -->
    <selectKey resultType="java.lang.Integer" keyProperty="id" order="BEFORE" >
      select nextval('seq_assess_option')
    </selectKey>
    insert into assess_option
    <trim prefix="(" suffix=")" suffixOverrides="," >
      id,
      <if test="name != null" >
        name,
      </if>
      <if test="status != null" >
        status,
      </if>
      <if test="creater != null" >
        creater,
      </if>
      <if test="createTime != null" >
        create_time,
      </if>
      <if test="modifier != null" >
        modifier,
      </if>
      <if test="modifyTime != null" >
        modify_time,
      </if>
      <if test="enableStatus != null" >
        enable_status,
      </if>
      <if test="remark != null" >
        remark,
      </if>
      <if test="point != null" >
        point,
      </if>
      <if test="reorder != null" >
        reorder,
      </if>
      <if test="keyword != null" >
        keyword,
      </if>
    </trim>
    <trim prefix="values (" suffix=")" suffixOverrides="," >
      #{id,jdbcType=INTEGER},
      <if test="name != null" >
        #{name,jdbcType=VARCHAR},
      </if>
      <if test="status != null" >
        #{status,jdbcType=VARCHAR},
      </if>
      <if test="creater != null" >
        #{creater,jdbcType=VARCHAR},
      </if>
      <if test="createTime != null" >
        #{createTime,jdbcType=TIMESTAMP},
      </if>
      <if test="modifier != null" >
        #{modifier,jdbcType=VARCHAR},
      </if>
      <if test="modifyTime != null" >
        #{modifyTime,jdbcType=TIMESTAMP},
      </if>
      <if test="enableStatus != null" >
        #{enableStatus,jdbcType=VARCHAR},
      </if>
      <if test="remark != null" >
        #{remark,jdbcType=VARCHAR},
      </if>
      <if test="point != null" >
        #{point,jdbcType=INTEGER},
      </if>
      <if test="reorder != null" >
        #{reorder,jdbcType=INTEGER},
      </if>
      <if test="keyword != null" >
        #{keyword,jdbcType=VARCHAR},
      </if>
    </trim>
  </insert>
  <select id="countByExample" parameterType="com.redfinger.manager.common.domain.AssessOptionExample" resultType="java.lang.Integer" >
    <!--
      WARNING - @mbggenerated
      This element is automatically generated by MyBatis Generator, do not modify.
      This element was generated on Wed Mar 23 14:42:45 CST 2016.
    -->
    select count(*) from assess_option
    <if test="_parameter != null" >
      <include refid="Example_Where_Clause" />
    </if>
  </select>
  <update id="updateByExampleSelective" parameterType="map" >
    <!--
      WARNING - @mbggenerated
      This element is automatically generated by MyBatis Generator, do not modify.
      This element was generated on Wed Mar 23 14:42:45 CST 2016.
    -->
    update assess_option
    <set >
      <if test="record.id != null" >
        id = #{record.id,jdbcType=INTEGER},
      </if>
      <if test="record.name != null" >
        name = #{record.name,jdbcType=VARCHAR},
      </if>
      <if test="record.status != null" >
        status = #{record.status,jdbcType=VARCHAR},
      </if>
      <if test="record.creater != null" >
        creater = #{record.creater,jdbcType=VARCHAR},
      </if>
      <if test="record.createTime != null" >
        create_time = #{record.createTime,jdbcType=TIMESTAMP},
      </if>
      <if test="record.modifier != null" >
        modifier = #{record.modifier,jdbcType=VARCHAR},
      </if>
      <if test="record.modifyTime != null" >
        modify_time = #{record.modifyTime,jdbcType=TIMESTAMP},
      </if>
      <if test="record.enableStatus != null" >
        enable_status = #{record.enableStatus,jdbcType=VARCHAR},
      </if>
      <if test="record.remark != null" >
        remark = #{record.remark,jdbcType=VARCHAR},
      </if>
      <if test="record.point != null" >
        point = #{record.point,jdbcType=INTEGER},
      </if>
      <if test="record.reorder != null" >
        reorder = #{record.reorder,jdbcType=INTEGER},
      </if>
      <if test="record.keyword != null" >
        keyword = #{record.keyword,jdbcType=VARCHAR},
      </if>
    </set>
    <if test="_parameter != null" >
      <include refid="Update_By_Example_Where_Clause" />
    </if>
  </update>
  <update id="updateByExample" parameterType="map" >
    <!--
      WARNING - @mbggenerated
      This element is automatically generated by MyBatis Generator, do not modify.
      This element was generated on Wed Mar 23 14:42:45 CST 2016.
    -->
    update assess_option
    set id = #{record.id,jdbcType=INTEGER},
      name = #{record.name,jdbcType=VARCHAR},
      status = #{record.status,jdbcType=VARCHAR},
      creater = #{record.creater,jdbcType=VARCHAR},
      create_time = #{record.createTime,jdbcType=TIMESTAMP},
      modifier = #{record.modifier,jdbcType=VARCHAR},
      modify_time = #{record.modifyTime,jdbcType=TIMESTAMP},
      enable_status = #{record.enableStatus,jdbcType=VARCHAR},
      remark = #{record.remark,jdbcType=VARCHAR},
      point = #{record.point,jdbcType=INTEGER},
      reorder = #{record.reorder,jdbcType=INTEGER},
      keyword = #{record.keyword,jdbcType=VARCHAR}
    <if test="_parameter != null" >
      <include refid="Update_By_Example_Where_Clause" />
    </if>
  </update>
  <update id="updateByPrimaryKeySelective" parameterType="com.redfinger.manager.common.domain.AssessOption" >
    <!--
      WARNING - @mbggenerated
      This element is automatically generated by MyBatis Generator, do not modify.
      This element was generated on Wed Mar 23 14:42:45 CST 2016.
    -->
    update assess_option
    <set >
      <if test="name != null" >
        name = #{name,jdbcType=VARCHAR},
      </if>
      <if test="status != null" >
        status = #{status,jdbcType=VARCHAR},
      </if>
      <if test="creater != null" >
        creater = #{creater,jdbcType=VARCHAR},
      </if>
      <if test="createTime != null" >
        create_time = #{createTime,jdbcType=TIMESTAMP},
      </if>
      <if test="modifier != null" >
        modifier = #{modifier,jdbcType=VARCHAR},
      </if>
      <if test="modifyTime != null" >
        modify_time = #{modifyTime,jdbcType=TIMESTAMP},
      </if>
      <if test="enableStatus != null" >
        enable_status = #{enableStatus,jdbcType=VARCHAR},
      </if>
      <if test="remark != null" >
        remark = #{remark,jdbcType=VARCHAR},
      </if>
      <if test="point != null" >
        point = #{point,jdbcType=INTEGER},
      </if>
      <if test="reorder != null" >
        reorder = #{reorder,jdbcType=INTEGER},
      </if>
      <if test="keyword != null" >
        keyword = #{keyword,jdbcType=VARCHAR},
      </if>
    </set>
    where id = #{id,jdbcType=INTEGER}
  </update>
  <update id="updateByPrimaryKey" parameterType="com.redfinger.manager.common.domain.AssessOption" >
    <!--
      WARNING - @mbggenerated
      This element is automatically generated by MyBatis Generator, do not modify.
      This element was generated on Wed Mar 23 14:42:45 CST 2016.
    -->
    update assess_option
    set name = #{name,jdbcType=VARCHAR},
      status = #{status,jdbcType=VARCHAR},
      creater = #{creater,jdbcType=VARCHAR},
      create_time = #{createTime,jdbcType=TIMESTAMP},
      modifier = #{modifier,jdbcType=VARCHAR},
      modify_time = #{modifyTime,jdbcType=TIMESTAMP},
      enable_status = #{enableStatus,jdbcType=VARCHAR},
      remark = #{remark,jdbcType=VARCHAR},
      point = #{point,jdbcType=INTEGER},
      reorder = #{reorder,jdbcType=INTEGER},
      keyword = #{keyword,jdbcType=VARCHAR}
    where id = #{id,jdbcType=INTEGER}
  </update>
  <select id="selectOneByExample" resultMap="BaseResultMap" parameterType="com.redfinger.manager.common.domain.AssessOptionExample" >
    <!--
      WARNING - @mbggenerated
      This element is automatically generated by MyBatis Generator, do not modify.
      This element was generated on Wed Mar 23 14:42:45 CST 2016.
    -->
    select 
    <include refid="Base_Column_List" />
    from assess_option
    <if test="_parameter != null" >
      <include refid="Example_Where_Clause" />
    </if>
    <if test="orderByClause != null" >
      order by ${orderByClause}
    </if>
    offset 0 limit 1
  </select>
  <select id="selectByExampleShowField" resultMap="BaseResultMap" parameterType="map" >
    <!--
      WARNING - @mbggenerated
      This element is automatically generated by MyBatis Generator, do not modify.
      This element was generated on Wed Mar 23 14:42:45 CST 2016.
    -->
    select 
    <foreach collection="showField" item="one" separator="," >
      ${one}
    </foreach>
    from assess_option
    <if test="example != null" >
      <include refid="Update_By_Example_Where_Clause" />
    </if>
    <if test="example.orderByClause != null" >
      order by ${example.orderByClause}
    </if>
  </select>
  <select id="selectOneByExampleShowField" resultMap="BaseResultMap" parameterType="map" >
    <!--
      WARNING - @mbggenerated
      This element is automatically generated by MyBatis Generator, do not modify.
      This element was generated on Wed Mar 23 14:42:45 CST 2016.
    -->
    select 
    <foreach collection="showField" item="one" separator="," >
      ${one}
    </foreach>
    from assess_option
    <if test="example != null" >
      <include refid="Update_By_Example_Where_Clause" />
    </if>
    <if test="example.orderByClause != null" >
      order by ${example.orderByClause}
    </if>
    offset 0 limit 1
  </select>
  <insert id="insertBatch" parameterType="java.util.List" >
    <!--
      WARNING - @mbggenerated
      This element is automatically generated by MyBatis Generator, do not modify.
      This element was generated on Wed Mar 23 14:42:45 CST 2016.
    -->
     insert into assess_option (id, name, status, creater, create_time, modifier, modify_time, 
    enable_status, remark, point, reorder, keyword
     ) values 
    <foreach collection="list" separator="," item="one" >
      ((select nextval('seq_assess_option')), #{one.name,jdbcType=VARCHAR}, #{one.status,jdbcType=VARCHAR}, 
      #{one.creater,jdbcType=VARCHAR}, #{one.createTime,jdbcType=TIMESTAMP}, #{one.modifier,jdbcType=VARCHAR}, 
      #{one.modifyTime,jdbcType=TIMESTAMP}, #{one.enableStatus,jdbcType=VARCHAR}, #{one.remark,jdbcType=VARCHAR}, 
      #{one.point,jdbcType=INTEGER}, #{one.reorder,jdbcType=INTEGER}, #{one.keyword,jdbcType=VARCHAR}
      )
    </foreach>
  </insert>
  <update id="updateByExampleSelectiveSync" parameterType="map" >
    <!--
      WARNING - @mbggenerated
      This element is automatically generated by MyBatis Generator, do not modify.
      This element was generated on Wed Mar 23 14:42:45 CST 2016.
    -->
    update assess_option
    <set >
      <if test="record.point != null" >
        point = (case when point is null then #{record.point,jdbcType=INTEGER} else point + #{record.point,jdbcType=INTEGER} end ),
      </if>
      <if test="record.reorder != null" >
        reorder = (case when reorder is null then #{record.reorder,jdbcType=INTEGER} else reorder + #{record.reorder,jdbcType=INTEGER} end ),
      </if>
    </set>
    <if test="_parameter != null" >
      <include refid="Update_By_Example_Where_Clause" />
    </if>
  </update>
  <update id="updateByPrimaryKeySelectiveSync" parameterType="com.redfinger.manager.common.domain.AssessOption" >
    <!--
      WARNING - @mbggenerated
      This element is automatically generated by MyBatis Generator, do not modify.
      This element was generated on Wed Mar 23 14:42:45 CST 2016.
    -->
    update assess_option
    <set >
      <if test="point != null" >
        point = (case when point is null then #{point,jdbcType=INTEGER} else point + #{point,jdbcType=INTEGER} end ),
      </if>
      <if test="reorder != null" >
        reorder = (case when reorder is null then #{reorder,jdbcType=INTEGER} else reorder + #{reorder,jdbcType=INTEGER} end ),
      </if>
    </set>
    where id = #{id,jdbcType=INTEGER}
  </update>
  <select id="selectByPrimaryKeyShowField" resultMap="BaseResultMap" parameterType="map" >
    <!--
      WARNING - @mbggenerated
      This element is automatically generated by MyBatis Generator, do not modify.
      This element was generated on Wed Mar 23 14:42:45 CST 2016.
    -->
    select 
    <foreach collection="showField" item="one" separator="," >
      ${one}
    </foreach>
    from assess_option
    where id = #{id,jdbcType=INTEGER}
  </select>
</mapper>